readme2word/__init__.py
readme2word/cli.py
readme2word/converter.py
readme2word/web.py
readme2word_converter_vm-1.0.5.dist-info/licenses/LICENSE
readme2word_converter_vm-1.0.5.dist-info/METADATA
readme2word_converter_vm-1.0.5.dist-info/WHEEL
readme2word_converter_vm-1.0.5.dist-info/entry_points.txt
readme2word_converter_vm-1.0.5.dist-info/top_level.txt
readme2word_converter_vm-1.0.5.dist-info/RECORD
