Metadata-Version: 2.4
Name: readme2word-converter-vm
Version: 1.0.5
Summary: Convert README.md files to professional Word documents with Mermaid diagram support
Home-page: https://github.com/vishalm/readme2readall
Author: Vishal Mishra
Author-email: Vishal Mishra <vishal@example.com>
License: MIT
Project-URL: Homepage, https://github.com/vishalm/readme2readall
Project-URL: Documentation, https://github.com/vishalm/readme2readall#readme
Project-URL: Repository, https://github.com/vishalm/readme2readall
Project-URL: Bug Tracker, https://github.com/vishalm/readme2readall/issues
Project-URL: Changelog, https://github.com/vishalm/readme2readall/releases
Keywords: readme,markdown,word,docx,converter,mermaid,diagrams,documentation,office,document,export,technical-writing
Classifier: Development Status :: 4 - Beta
Classifier: Intended Audience :: Developers
Classifier: Intended Audience :: End Users/Desktop
Classifier: Topic :: Documentation
Classifier: Topic :: Office/Business :: Office Suites
Classifier: Topic :: Software Development :: Documentation
Classifier: Topic :: Text Processing :: Markup :: Markdown
Classifier: Programming Language :: Python :: 3
Classifier: Programming Language :: Python :: 3.8
Classifier: Programming Language :: Python :: 3.9
Classifier: Programming Language :: Python :: 3.10
Classifier: Programming Language :: Python :: 3.11
Classifier: Programming Language :: Python :: 3.12
Classifier: Operating System :: OS Independent
Classifier: Environment :: Web Environment
Requires-Python: >=3.8
License-File: LICENSE
Requires-Dist: streamlit>=1.28.0
Requires-Dist: python-docx>=0.8.11
Requires-Dist: markdown>=3.5.0
Requires-Dist: beautifulsoup4>=4.12.0
Requires-Dist: requests>=2.31.0
Requires-Dist: Pillow>=10.0.0
Provides-Extra: dev
Requires-Dist: pytest>=7.0.0; extra == "dev"
Requires-Dist: pytest-cov>=4.0.0; extra == "dev"
Requires-Dist: pytest-timeout>=2.1.0; extra == "dev"
Requires-Dist: black>=23.0.0; extra == "dev"
Requires-Dist: flake8>=6.0.0; extra == "dev"
Requires-Dist: isort>=5.12.0; extra == "dev"
Requires-Dist: mypy>=1.0.0; extra == "dev"
Requires-Dist: pre-commit>=3.0.0; extra == "dev"
Requires-Dist: safety>=2.3.0; extra == "dev"
Requires-Dist: bandit>=1.7.0; extra == "dev"
Requires-Dist: types-Markdown>=3.7.0; extra == "dev"
Requires-Dist: types-requests>=2.32.0; extra == "dev"
Provides-Extra: docker
Requires-Dist: docker>=6.0.0; extra == "docker"
Provides-Extra: kubernetes
Requires-Dist: kubernetes>=25.0.0; extra == "kubernetes"
Requires-Dist: pyyaml>=6.0; extra == "kubernetes"
Provides-Extra: all
Requires-Dist: readme2word-converter-vm[dev,docker,kubernetes]; extra == "all"
Dynamic: author
Dynamic: home-page
Dynamic: license-file
Dynamic: requires-python
